openllmtelemetry/__init__.py
openllmtelemetry/config.py
openllmtelemetry/content_id/__init__.py
openllmtelemetry/guardrails/__init__.py
openllmtelemetry/guardrails/client.py
openllmtelemetry/guardrails/handlers.py
openllmtelemetry/instrument.py
openllmtelemetry/instrumentation/__init__.py
openllmtelemetry/instrumentation/bedrock/__init__.py
openllmtelemetry/instrumentation/bedrock/reusable_streaming_body.py
openllmtelemetry/instrumentation/decorators/__init__.py
openllmtelemetry/instrumentation/decorators/task.py
openllmtelemetry/instrumentation/openai/__init__.py
openllmtelemetry/instrumentation/openai/shared/__init__.py
openllmtelemetry/instrumentation/openai/shared/chat_wrappers.py
openllmtelemetry/instrumentation/openai/shared/completion_wrappers.py
openllmtelemetry/instrumentation/openai/shared/embeddings_wrappers.py
openllmtelemetry/instrumentation/openai/utils.py
openllmtelemetry/instrumentation/openai/v0/__init__.py
openllmtelemetry/instrumentation/openai/v1/__init__.py
openllmtelemetry/instrumentation/openai/version.py
openllmtelemetry/instrumentation/watsonx/__init__.py
openllmtelemetry/instrumentation/watsonx/config.py
openllmtelemetry/instrumentation/watsonx/utils.py
openllmtelemetry/instrumentors.py
openllmtelemetry/semantic_conventions/gen_ai/__init__.py
openllmtelemetry/span_exporter.py
openllmtelemetry/version.py
openllmtelemetry-0.0.8.dist-info/LICENSE
openllmtelemetry-0.0.8.dist-info/METADATA
openllmtelemetry-0.0.8.dist-info/WHEEL
openllmtelemetry-0.0.8.dist-info/RECORD
