Metadata-Version: 2.1
Name: OpenLLMTelemetry
Version: 0.0.8
Summary: End-to-end observability with built-in security guardrails.
License: Apache-2.0
Author: WhyLabs.ai
Author-email: support@whylabs.ai
Requires-Python: >=3.8.1,<4.0
Classifier: License :: OSI Approved :: Apache Software License
Classifier: Programming Language :: Python :: 3
Classifier: Programming Language :: Python :: 3.9
Classifier: Programming Language :: Python :: 3.10
Classifier: Programming Language :: Python :: 3.11
Provides-Extra: bedrock
Provides-Extra: openai
Requires-Dist: boto3 (>=1.18.67,<2.0.0) ; extra == "bedrock"
Requires-Dist: openai (>=0.27,<2.0) ; extra == "openai"
Requires-Dist: opentelemetry-api (>=1.21.0,<2.0.0)
Requires-Dist: opentelemetry-exporter-otlp-proto-http (>=1.22.0,<2.0.0)
Requires-Dist: opentelemetry-instrumentation-requests (>=0.43b0,<0.44)
Requires-Dist: opentelemetry-sdk (>=1.21.0,<2.0.0)
Requires-Dist: packaging
Requires-Dist: whylogs-container-client (>=2.0.2,<3.0.0)
